lightberry_ai/__init__.py
lightberry_ai/auth/__init__.py
lightberry_ai/auth/authenticator.py
lightberry_ai/auth/custom_authenticator.py
lightberry_ai/auth/local_authenticator.py
lightberry_ai/core/__init__.py
lightberry_ai/core/audio_streaming.py
lightberry_ai/core/basic_client.py
lightberry_ai/core/tool_client.py
lightberry_ai/core/tool_streaming.py
lightberry_ai/tools/__init__.py
lightberry_ai/tools/server.py
lightberry_ai/utils/__init__.py
lightberry_ai-0.1.1.dist-info/licenses/LICENSE
lightberry_ai-0.1.1.dist-info/METADATA
lightberry_ai-0.1.1.dist-info/WHEEL
lightberry_ai-0.1.1.dist-info/top_level.txt
lightberry_ai-0.1.1.dist-info/RECORD
