Metadata-Version: 2.4
Name: lightberry-ai
Version: 0.1.1
Summary: Lightberry voice AI SDK for robots
Author-email: Lightberry AI <info@lightberry.ai>
License: MIT
Project-URL: Homepage, https://lightberry.ai
Project-URL: Repository, https://github.com/lightberry-ai/lightberry-python-sdk
Project-URL: Documentation, https://docs.lightberry.ai
Project-URL: Bug Tracker, https://github.com/lightberry-ai/lightberry-python-sdk/issues
Keywords: livekit,audio,streaming,real-time,tools,ai
Classifier: Development Status :: 3 - Alpha
Classifier: Intended Audience :: Developers
Classifier: License :: OSI Approved :: MIT License
Classifier: Programming Language :: Python :: 3
Classifier: Programming Language :: Python :: 3.10
Classifier: Programming Language :: Python :: 3.11
Classifier: Topic :: Multimedia :: Sound/Audio
Classifier: Topic :: Communications :: Conferencing
Requires-Python: >=3.10
License-File: LICENSE
Requires-Dist: livekit>=0.10.0
Requires-Dist: livekit-api>=0.5.0
Requires-Dist: sounddevice>=0.4.0
Requires-Dist: python-dotenv>=1.0.0
Requires-Dist: numpy>=1.21.0
Requires-Dist: aiohttp>=3.8.0
Provides-Extra: dev
Requires-Dist: pytest>=7.0.0; extra == "dev"
Requires-Dist: pytest-asyncio>=0.21.0; extra == "dev"
Requires-Dist: black>=22.0.0; extra == "dev"
Requires-Dist: flake8>=5.0.0; extra == "dev"
Requires-Dist: mypy>=1.0.0; extra == "dev"
Dynamic: license-file
Dynamic: requires-python
